-- BYTECODE -- learn_bytecode.lua:0-15
0001    TDUP     0   0
0002    GSET     0   1      ; "EquipPos"
0003    TDUP     0   2
0004    GSET     0   3      ; "td"
0005    GGET     0   4      ; "print"
0006    GGET     1   3      ; "td"
0007    GGET     2   1      ; "EquipPos"
0008    TGETS    2   2   5  ; "PosHelmet"
0009    TGETV    1   1   2
0010    CALL     0   1   2
0011    GGET     0   4      ; "print"
0012    GGET     1   3      ; "td"
0013    TGETB    1   1   2
0014    CALL     0   1   2
0015    RET0     0   1

